kiwiml/__init__.py
kiwiml/autodiff.py
kiwiml/datasets.py
kiwiml-0.0.5.dist-info/LICENSE
kiwiml-0.0.5.dist-info/METADATA
kiwiml-0.0.5.dist-info/WHEEL
kiwiml-0.0.5.dist-info/top_level.txt
kiwiml-0.0.5.dist-info/RECORD
