Metadata-Version: 2.1
Name: kiwiml
Version: 0.0.5
Summary: a tiny, simple, instructional machine learning library in python
Home-page: https://github.com/oriyonay/kiwiml
Author: Ori Yonay
Author-email: oriyonay12@gmail.com
License: UNKNOWN
Platform: UNKNOWN
Classifier: Programming Language :: Python :: 3
Classifier: License :: OSI Approved :: MIT License
Classifier: Operating System :: OS Independent
Requires-Python: >=3.6
